odoo/addons/stock_putaway_same_location/README.rst
odoo/addons/stock_putaway_same_location/__init__.py
odoo/addons/stock_putaway_same_location/__manifest__.py
odoo/addons/stock_putaway_same_location/i18n/stock_putaway_same_location.pot
odoo/addons/stock_putaway_same_location/models/__init__.py
odoo/addons/stock_putaway_same_location/models/product_putaway.py
odoo/addons/stock_putaway_same_location/models/stock_move.py
odoo/addons/stock_putaway_same_location/static/description/icon.png
odoo/addons/stock_putaway_same_location/tests/__init__.py
odoo/addons/stock_putaway_same_location/tests/test_same_location_putaway_strategy.py
odoo11_addon_stock_putaway_same_location-11.0.1.0.0.99.dev3.dist-info/METADATA
odoo11_addon_stock_putaway_same_location-11.0.1.0.0.99.dev3.dist-info/WHEEL
odoo11_addon_stock_putaway_same_location-11.0.1.0.0.99.dev3.dist-info/top_level.txt
odoo11_addon_stock_putaway_same_location-11.0.1.0.0.99.dev3.dist-info/RECORD
